LAB0/q1.v
module q1(x1,x2,x3,f);

input x1,x2,x3;
output f;

assign f = (x1 | x2) & (~(x2) | x3);

endmodule

LAB0/q1_tb.v
`timescale 1ns/1ns
`include "q1.v"

module q1_tb();

reg x1,x2,x3;
wire f;

q1 ins_q1(x1,x2,x3,f);

initial
begin

$dumpfile("q1_tb.vcd");
$dumpvars(0,q1_tb);

x1=0;x2=0;x3=0;
#10;
x1=0;x2=0;x3=1;
#10;
x1=0;x2=1;x3=0;
#10;
x1=1;x2=0;x3=0;
#10;
x1=0;x2=1;x3=1;
#10;
x1=1;x2=0;x3=1;
#10;
x1=1;x2=1;x3=0;
#10;
x1=1;x2=1;x3=1;
#10;

end
endmodule

LAB0/q1_tb.vcd
$date
	Sun Aug 24 19:22:29 2025
$end
$version
	Icarus Verilog
$end
$timescale
	1ns
$end
$scope module q1_tb $end
$var wire 1 ! f $end
$var reg 1 " x1 $end
$var reg 1 # x2 $end
$var reg 1 $ x3 $end
$scope module ins_q1 $end
$var wire 1 ! f $end
$var wire 1 " x1 $end
$var wire 1 # x2 $end
$var wire 1 $ x3 $end
$upscope $end
$upscope $end
$enddefinitions $end
$comment Show the parameter values. $end
$dumpall
$end
#0
$dumpvars
0$
0#
0"
0!
$end
#10
1$
#20
0$
1#
#30
1!
0#
1"
#40
1$
1#
0"
#50
0#
1"
#60
0!
0$
1#
#70
1!
1$
