LAB8/DFF.v
module DFF(D,clk,Q,reset);

input D,clk,reset;
output reg Q;

always @(posedge clk, posedge reset)begin
    if(reset)
        Q<=0;
    else
        Q<=D;
end
endmodule

LAB8/shiftReg6Bit.v
`include "DFF.v"
module shiftReg6Bit(W,clk,Q,clr);

input W,clk,clr;
output [5:0]Q;
DFF DFF_ins1(W,clk,Q[5],clr);
DFF DFF_ins2(Q[5],clk,Q[4],clr);
DFF DFF_ins3(Q[4],clk,Q[3],clr);
DFF DFF_ins4(Q[3],clk,Q[2],clr);
DFF DFF_ins5(Q[2],clk,Q[1],clr);
DFF DFF_ins6(Q[1],clk,Q[0],clr);
endmodule

LAB8/shiftReg6Bit_tb.v
`include "shiftReg6Bit.v"
`timescale 1ns/1ns

module shiftReg6Bit_tb();

reg W,clk,clr;
wire [5:0]Q;

shiftReg6Bit shiftReg6Bit_ins(W,clk,Q,clr);

initial begin
    $dumpfile("shiftReg6Bit_tb.vcd");
    $dumpvars(0,shiftReg6Bit_tb);
end

initial begin
    clk = 0;
    forever #10 clk = ~clk;
end

initial begin
    clr = 1;
    #5;
    clr = 0;
    W = 1'b0;  #10;
    W = 1'b1;  #10;   
    W = 1'b0;  #20;
    W = 1'b1;  #20;
    W = 1'b1;  #20;
    W = 1'b0;  #20;
    W = 1'b0;  #20;  
    $finish;
end
endmodule

LAB8/shiftReg6Bit_tb.vcd
$date
	Tue Oct 21 16:11:13 2025
$end
$version
	Icarus Verilog
$end
$timescale
	1ns
$end
$scope module shiftReg6Bit_tb $end
$var wire 6 ! Q [5:0] $end
$var reg 1 " W $end
$var reg 1 # clk $end
$var reg 1 $ clr $end
$scope module shiftReg6Bit_ins $end
$var wire 1 " W $end
$var wire 1 # clk $end
$var wire 1 $ clr $end
$var wire 6 % Q [5:0] $end
$scope module DFF_ins1 $end
$var wire 1 " D $end
$var wire 1 # clk $end
$var wire 1 $ reset $end
$var reg 1 & Q $end
$upscope $end
$scope module DFF_ins2 $end
$var wire 1 ' D $end
$var wire 1 # clk $end
$var wire 1 $ reset $end
$var reg 1 ( Q $end
$upscope $end
$scope module DFF_ins3 $end
$var wire 1 ) D $end
$var wire 1 # clk $end
$var wire 1 $ reset $end
$var reg 1 * Q $end
$upscope $end
$scope module DFF_ins4 $end
$var wire 1 + D $end
$var wire 1 # clk $end
$var wire 1 $ reset $end
$var reg 1 , Q $end
$upscope $end
$scope module DFF_ins5 $end
$var wire 1 - D $end
$var wire 1 # clk $end
$var wire 1 $ reset $end
$var reg 1 . Q $end
$upscope $end
$scope module DFF_ins6 $end
$var wire 1 / D $end
$var wire 1 # clk $end
$var wire 1 $ reset $end
$var reg 1 0 Q $end
$upscope $end
$upscope $end
$upscope $end
$enddefinitions $end
$comment Show the parameter values. $end
$dumpall
$end
#0
$dumpvars
00
0/
0.
0-
0,
0+
0*
0)
0(
0'
0&
b0 %
1$
0#
x"
b0 !
$end
#5
0"
0$
#10
1#
#15
1"
#20
0#
#25
0"
#30
1#
#40
0#
#45
1"
#50
1'
b100000 !
b100000 %
1&
1#
#60
0#
#70
1)
b110000 !
b110000 %
1(
1#
#80
0#
#85
0"
#90
1+
0'
1*
b11000 !
b11000 %
0&
1#
#100
0#
#110
0)
1-
0(
b1100 !
b1100 %
1,
1#
