LAB5/MUX2to1.v
module MUX2to1(w,s,f);

input [0:1]w;
input s;
output reg f;

always @(*) begin
    if(s == 1'b0)
    begin
        f = w[0];
    end
    else
    begin
        f = w[1];
    end
end

endmodule

LAB5/MUX8to1.v
module MUX8to1(w,s,f);

input [0:7]w;
input [2:0]s;

output reg f;

always @(*) begin

    case (s)
        3'b000 : f = w[0];
        3'b001 : f = w[1];
        3'b010 : f = w[2];
        3'b011 : f = w[3];
        3'b100 : f = w[4];
        3'b101 : f = w[5];
        3'b110 : f = w[6];
        3'b111 : f = w[7];
        default: f = 0;
    endcase

end

endmodule

LAB5/MUX16to1_8to1.v
`include "MUX8to1.v"
`include "MUX2to1.v"
module MUX16to1_8to1(w,s,f);

input [0:15]w;
input [3:0]s;

output f;

wire [0:1]x;

MUX8to1 stage0a(w[0:7],s[2:0],x[0]);
MUX8to1 stage0b(w[8:15],s[2:0],x[1]);

MUX2to1 stage1(x,s[3],f);

endmodule

LAB5/MUX16to1_8to1_tb.v
`timescale 1ns/1ns
`include "MUX16to1_8to1.v"

module MUX16to1_8to1_tb();

reg[0:15] w;
reg [3:0] s;
wire f;

MUX16to1_8to1 MUX16to1_8to1_ins(w,s,f);

initial
begin

$dumpfile("MUX16to1_8to1_tb.vcd");
$dumpvars(0,MUX16to1_8to1_tb);


    w = 16'b1010_1100_1101_0001; s = 4'b0000;
    #10;
    w = 16'b1010_1100_1101_0001; s = 4'b0001;
    #10;
    w = 16'b1010_1100_1101_0001; s = 4'b0010;
    #10;
    w = 16'b1010_1100_1101_0001; s = 4'b0011;
    #10;
    w = 16'b1010_1100_1101_0001; s = 4'b0100;
    #10;
    w = 16'b1010_1100_1101_0001; s = 4'b0101;
    #10;
    w = 16'b1010_1100_1101_0001; s = 4'b0110;
    #10;
    w = 16'b1010_1100_1101_0001; s = 4'b0111;
    #10;
    w = 16'b1010_1100_1101_0001; s = 4'b1000;
    #10;
    w = 16'b1010_1100_1101_0001; s = 4'b1001;
    #10;
    w = 16'b1010_1100_1101_0001; s = 4'b1010;
    #10;
    w = 16'b1010_1100_1101_0001; s = 4'b1011;
    #10;
    w = 16'b1010_1100_1101_0001; s = 4'b1100;
    #10;
    w = 16'b1010_1100_1101_0001; s = 4'b1101;
    #10;
    w = 16'b1010_1100_1101_0001; s = 4'b1110;
    #10;
    w = 16'b1010_1100_1101_0001; s = 4'b1111;
    #10;

end
endmodule

LAB5/MUX16to1_8to1_tb.vcd
$date
	Wed Sep 03 00:51:45 2025
$end
$version
	Icarus Verilog
$end
$timescale
	1ns
$end
$scope module MUX16to1_8to1_tb $end
$var wire 1 ! f $end
$var reg 4 " s [3:0] $end
$var reg 16 # w [0:15] $end
$scope module MUX16to1_8to1_ins $end
$var wire 4 $ s [3:0] $end
$var wire 16 % w [0:15] $end
$var wire 2 & x [0:1] $end
$var wire 1 ! f $end
$scope module stage0a $end
$var wire 3 ' s [2:0] $end
$var wire 8 ( w [0:7] $end
$var reg 1 ) f $end
$upscope $end
$scope module stage0b $end
$var wire 3 * s [2:0] $end
$var wire 8 + w [0:7] $end
$var reg 1 , f $end
$upscope $end
$scope module stage1 $end
$var wire 1 - s $end
$var wire 2 . w [0:1] $end
$var reg 1 ! f $end
$upscope $end
$upscope $end
$upscope $end
$enddefinitions $end
$comment Show the parameter values. $end
$dumpall
$end
#0
$dumpvars
b11 .
0-
1,
b11010001 +
b0 *
1)
b10101100 (
b0 '
b11 &
b1010110011010001 %
b0 $
b1010110011010001 #
b0 "
1!
$end
#10
0!
b1 &
b1 .
0)
b1 '
b1 *
b1 "
b1 $
#20
1!
1)
b10 &
b10 .
0,
b10 '
b10 *
b10 "
b10 $
#30
0!
0)
b1 &
b1 .
1,
b11 '
b11 *
b11 "
b11 $
#40
1!
1)
b10 &
b10 .
0,
b100 '
b100 *
b100 "
b100 $
#50
b101 '
b101 *
b101 "
b101 $
#60
0!
b0 &
b0 .
0)
b110 '
b110 *
b110 "
b110 $
#70
b1 &
b1 .
1,
b111 '
b111 *
b111 "
b111 $
#80
b11 &
b11 .
1)
1!
b0 '
b0 *
1-
b1000 "
b1000 $
#90
b1 &
b1 .
0)
b1 '
b1 *
b1001 "
b1001 $
#100
0!
1)
b10 &
b10 .
0,
b10 '
b10 *
b1010 "
b1010 $
#110
1!
0)
b1 &
b1 .
1,
b11 '
b11 *
b1011 "
b1011 $
#120
0!
1)
b10 &
b10 .
0,
b100 '
b100 *
b1100 "
b1100 $
#130
b101 '
b101 *
b1101 "
b1101 $
#140
b0 &
b0 .
0)
b110 '
b110 *
b1110 "
b1110 $
#150
1!
b1 &
b1 .
1,
b111 '
b111 *
b1111 "
b1111 $
