LAB5/MUX8to1.v
module MUX8to1(w,s,f);

input [0:7]w;
input [2:0]s;

output reg f;

always @(*) begin

    case (s)
        3'b000 : f = w[0];
        3'b001 : f = w[1];
        3'b010 : f = w[2];
        3'b011 : f = w[3];
        3'b100 : f = w[4];
        3'b101 : f = w[5];
        3'b110 : f = w[6];
        3'b111 : f = w[7];
        default: f = 0;
    endcase

end

endmodule

LAB5/MUX8to1_tb.v
`timescale 1ns/1ns
`include "MUX8to1.v"

module MUX8to1_tb();

reg[0:7] w;
reg [2:0] s;
wire f;

MUX8to1 MUX8to1_ins(w,s,f);

initial
begin

$dumpfile("MUX8to1_tb.vcd");
$dumpvars(0,MUX8to1_tb);


//case 1:
    w = 8'b1010_1010; s = 3'b000;
    #10;
    w = 8'b1010_1010; s = 3'b001;
    #10;
    w = 8'b1010_1010; s = 3'b010;
    #10;
    w = 8'b1010_1010;  s = 3'b011;
    #10;
    w = 8'b1010_1010;  s = 3'b100;
    #10;
    w = 8'b1010_1010;  s = 3'b101;
    #10;
    w = 8'b1010_1010;  s = 3'b110;
    #10;
    w = 8'b1010_1010;  s = 3'b111;
    #10;

end
endmodule

LAB5/MUX8to1_tb.vcd
$date
	Wed Sep 03 00:43:38 2025
$end
$version
	Icarus Verilog
$end
$timescale
	1ns
$end
$scope module MUX8to1_tb $end
$var wire 1 ! f $end
$var reg 3 " s [2:0] $end
$var reg 8 # w [0:7] $end
$scope module MUX8to1_ins $end
$var wire 3 $ s [2:0] $end
$var wire 8 % w [0:7] $end
$var reg 1 ! f $end
$upscope $end
$upscope $end
$enddefinitions $end
$comment Show the parameter values. $end
$dumpall
$end
#0
$dumpvars
b10101010 %
b0 $
b10101010 #
b0 "
1!
$end
#10
0!
b1 "
b1 $
#20
1!
b10 "
b10 $
#30
0!
b11 "
b11 $
#40
1!
b100 "
b100 $
#50
0!
b101 "
b101 $
#60
1!
b110 "
b110 $
#70
0!
b111 "
b111 $
