LAB3/q3.v
module q3(a,b,c,d,f);

input a,b,c,d;
output f;

assign f = ~((~d) | ~(~a | ~c));

endmodule

LAB3/q3_tb.v
`timescale 1ns/1ns
`include "q3.v"

module q3_tb();

reg a,b,c,d;
wire f;

q3 ins_q3(a,b,c,d,f);

initial
begin

$dumpfile("q3_tb.vcd");
$dumpvars(0,q3_tb);

a=0;b=0;c=0;d=0;
#10;
a=0;b=0;c=0;d=1;
#10;
a=0;b=0;c=1;d=0;
#10;
a=0;b=0;c=1;d=1;
#10;
a=0;b=1;c=0;d=0;
#10;
a=0;b=1;c=0;d=1;
#10;
a=0;b=1;c=1;d=0;
#10;
a=0;b=1;c=1;d=1;
#10;
a=1;b=0;c=0;d=0;
#10;
a=1;b=0;c=0;d=1;
#10;
a=1;b=0;c=1;d=0;
#10;
a=1;b=0;c=1;d=1;
#10;
a=1;b=1;c=0;d=0;
#10;
a=1;b=1;c=0;d=1;
#10;
a=1;b=1;c=1;d=0;
#10;
a=1;b=1;c=1;d=1;
#10;

end
endmodule

LAB3/q3_tb.vcd
$date
	Mon Aug 25 15:25:55 2025
$end
$version
	Icarus Verilog
$end
$timescale
	1ns
$end
$scope module q3_tb $end
$var wire 1 ! f $end
$var reg 1 " a $end
$var reg 1 # b $end
$var reg 1 $ c $end
$var reg 1 % d $end
$scope module ins_q3 $end
$var wire 1 " a $end
$var wire 1 # b $end
$var wire 1 $ c $end
$var wire 1 % d $end
$var wire 1 ! f $end
$upscope $end
$upscope $end
$enddefinitions $end
$comment Show the parameter values. $end
$dumpall
$end
#0
$dumpvars
0%
0$
0#
0"
0!
$end
#10
1!
1%
#20
0!
0%
1$
#30
1!
1%
#40
0!
0%
0$
1#
#50
1!
1%
#60
0!
0%
1$
#70
1!
1%
#80
0!
0%
0$
0#
1"
#90
1!
1%
#100
0!
0%
1$
#110
1%
#120
0%
0$
1#
#130
1!
1%
#140
0!
0%
1$
#150
1%
