LAB6/DEC2to4.v
module DEC2to4(en,w,y);

input en;
input [1:0]w;
output reg [0:3]y;

always @(*) begin
    if(en==0)begin
        y = 4'b0000;
    end
    else if(w==0)begin
        y = 4'b1000;
    end
    else if(w==1)begin
        y = 4'b0100;
    end
    else if(w==2)begin
        y = 4'b0010;
    end
    else begin
        y = 4'b0001;
    end
end
endmodule

LAB6/DEC3to8_2to4.v
`include "DEC2to4.v"
module DEC3to8_2to4(en,w,y);

input en;
input [2:0]w;
output [0:7]y;

DEC2to4 stage0((en&~w[2]),w[1:0],y[0:3]);
DEC2to4 stage1((en&w[2]),w[1:0],y[4:7]);

endmodule

LAB6/DEC3to8_2to4_tb.v
`include "DEC3to8_2to4.v"
`timescale 1ns/1ns

module DEC3to8_2to4_tb();

reg en;
reg [2:0]w;
wire [0:7]y;

DEC3to8_2to4 DEC3to8_2to4_ins(en,w,y);

initial begin

    $dumpfile("DEC3to8_2to4_tb.vcd");
    $dumpvars(0,DEC3to8_2to4_tb);

    for (integer i=0;i<8;i=i+1) begin
        en=0;w=i;
        #10;
    end
    for (integer i=0;i<8;i=i+1) begin
        en=1;w=i;
        #10;
    end
end
endmodule

LAB6/DEC3to8_2to4_tb.vcd
$date
	Sat Oct 18 17:12:21 2025
$end
$version
	Icarus Verilog
$end
$timescale
	1ns
$end
$scope module DEC3to8_2to4_tb $end
$var wire 8 ! y [0:7] $end
$var reg 1 " en $end
$var reg 3 # w [2:0] $end
$scope module DEC3to8_2to4_ins $end
$var wire 1 " en $end
$var wire 3 $ w [2:0] $end
$var wire 8 % y [0:7] $end
$scope module stage0 $end
$var wire 1 & en $end
$var wire 2 ' w [1:0] $end
$var reg 4 ( y [0:3] $end
$upscope $end
$scope module stage1 $end
$var wire 1 ) en $end
$var wire 2 * w [1:0] $end
$var reg 4 + y [0:3] $end
$upscope $end
$upscope $end
$scope begin $ivl_for_loop0 $end
$var integer 32 , i [31:0] $end
$upscope $end
$scope begin $ivl_for_loop1 $end
$var integer 32 - i [31:0] $end
$upscope $end
$upscope $end
$enddefinitions $end
$comment Show the parameter values. $end
$dumpall
$end
#0
$dumpvars
bx -
b0 ,
b0 +
b0 *
0)
b0 (
b0 '
0&
b0 %
b0 $
b0 #
0"
b0 !
$end
#10
b1 '
b1 *
b1 #
b1 $
b1 ,
#20
b10 '
b10 *
b10 #
b10 $
b10 ,
#30
b11 '
b11 *
b11 #
b11 $
b11 ,
#40
b0 '
b0 *
b100 #
b100 $
b100 ,
#50
b1 '
b1 *
b101 #
b101 $
b101 ,
#60
b10 '
b10 *
b110 #
b110 $
b110 ,
#70
b11 '
b11 *
b111 #
b111 $
b111 ,
#80
b1000 (
1&
b10000000 !
b10000000 %
b0 +
b0 '
b0 *
0)
b0 #
b0 $
1"
b0 -
b1000 ,
#90
b1000000 !
b1000000 %
b100 (
b1 '
b1 *
b1 #
b1 $
b1 -
#100
b100000 !
b100000 %
b10 (
b10 '
b10 *
b10 #
b10 $
b10 -
#110
b10000 !
b10000 %
b1 (
b11 '
b11 *
b11 #
b11 $
b11 -
#120
0&
b1000 +
b1000 !
b1000 %
b0 (
1)
b0 '
b0 *
b100 #
b100 $
b100 -
#130
b100 !
b100 %
b100 +
b1 '
b1 *
b101 #
b101 $
b101 -
#140
b10 !
b10 %
b10 +
b10 '
b10 *
b110 #
b110 $
b110 -
#150
b1 !
b1 %
b1 +
b11 '
b11 *
b111 #
b111 $
b111 -
#160
b1000 -
