LAB7/JKFF.v
module JKFF(J,K,clk,reset,Q);

input J,K,clk,reset;
output reg Q;

always @(posedge clk) begin
    if(reset) begin
        Q<=0;
    end
    else if(J==0) begin
        if(K==0) begin
            Q<=Q;
        end
        else begin
            Q<=0;
        end
    end
    else begin
        if(K==0) begin
            Q<=1;
        end
        else begin
            Q<=~Q;
        end
    end
end

endmodule

LAB7/JKFF_tb.v
`include "JKFF.v"
`timescale 1ps/1ps

module JKFF_tb();

reg J,K,clk,reset;
wire Q;

JKFF JKFF_ins(J,K,clk,reset,Q);

initial begin
    $dumpfile("JKFF_tb.vcd");
    $dumpvars(0,JKFF_tb);
end

initial begin
    clk = 0;
    forever #2 clk = ~clk;
end

initial begin
    J=0;K=0;reset=1;
    #2;
    J=0;K=1;reset=1;
    #2;
    J=1;K=0;reset=1;
    #2;
    J=1;K=1;reset=1;
    #2;
    J=0;K=0;reset=0;
    #2;
    J=0;K=1;reset=0;
    #2;
    J=1;K=0;reset=0;
    #2;
    J=1;K=1;reset=0;
    #2;
    $finish;
end

endmodule

LAB7/JKFF_tb.vcd
$date
	Sat Nov 01 16:35:25 2025
$end
$version
	Icarus Verilog
$end
$timescale
	1ps
$end
$scope module JKFF_tb $end
$var wire 1 ! Q $end
$var reg 1 " J $end
$var reg 1 # K $end
$var reg 1 $ clk $end
$var reg 1 % reset $end
$scope module JKFF_ins $end
$var wire 1 " J $end
$var wire 1 # K $end
$var wire 1 $ clk $end
$var wire 1 % reset $end
$var reg 1 ! Q $end
$upscope $end
$upscope $end
$enddefinitions $end
$comment Show the parameter values. $end
$dumpall
$end
#0
$dumpvars
1%
0$
0#
0"
x!
$end
#2
0!
1#
1$
#4
0#
1"
0$
#6
1#
1$
#8
0%
0#
0"
0$
#10
1#
1$
#12
0#
1"
0$
#14
1!
1#
1$
