LAB7/TFF.v
module TFF(T,clk,reset,Q);

input T,clk,reset;
output reg Q;

always @(negedge clk,negedge reset) begin
    if(!reset) begin
        Q<=0;
    end
    else begin
        if(T==0) begin
            Q<=Q;
        end
        else begin
            Q<=~Q;
        end
    end
end

endmodule

LAB7/TFF_tb.v
`include "TFF.v"
`timescale 1ps/1ps

module TFF_tb();

reg T,clk,reset;
wire Q;

TFF TFF_ins(T,clk,reset,Q);

initial begin
    $dumpfile("TFF_tb.vcd");
    $dumpvars(0,TFF_tb);
end

initial begin
    clk = 0;
    forever #2 clk = ~clk;
end

initial begin
    T=0;reset=0;
    #1;
    T=1;reset=0;
    #2;
    T=0;reset=1;
    #2;
    T=1;reset=1;
    #4;
    T=0;reset=1;
    #4;
    T=1;reset=1;
    #4;
    T=0;reset=1;
    $finish;
end

endmodule

LAB7/TFF_tb.vcd
$date
	Sat Nov 01 15:53:08 2025
$end
$version
	Icarus Verilog
$end
$timescale
	1ps
$end
$scope module TFF_tb $end
$var wire 1 ! Q $end
$var reg 1 " T $end
$var reg 1 # clk $end
$var reg 1 $ reset $end
$scope module TFF_ins $end
$var wire 1 " T $end
$var wire 1 # clk $end
$var wire 1 $ reset $end
$var reg 1 ! Q $end
$upscope $end
$upscope $end
$enddefinitions $end
$comment Show the parameter values. $end
$dumpall
$end
#0
$dumpvars
0$
0#
0"
0!
$end
#1
1"
#2
1#
#3
1$
0"
#4
0#
#5
1"
#6
1#
#8
1!
0#
#9
0"
#10
1#
#12
0#
#13
1"
#14
1#
#16
0!
0#
#17
0"
